{
  "associatedLayout": "menu",
  "name": "Menu_yes_or_no",
  "instances": [
    {
      "angle": 0,
      "customSize": true,
      "depth": 32,
      "height": 59,
      "layer": "yes_no",
      "name": "yes",
      "persistentUuid": "2a7b0fcb-2dd9-4a36-86f3-9a9c3598a146",
      "width": 256,
      "x": 308,
      "y": 441,
      "zOrder": 1,
      "numberProperties": [],
      "stringProperties": [],
      "initialVariables": []
    },
    {
      "angle": 0,
      "customSize": true,
      "depth": 32,
      "height": 59,
      "layer": "yes_no",
      "name": "no",
      "persistentUuid": "0d58d38a-f4b1-415b-951a-188a22082ef7",
      "width": 256,
      "x": 700,
      "y": 441,
      "zOrder": 2,
      "numberProperties": [],
      "stringProperties": [],
      "initialVariables": []
    },
    {
      "angle": 0,
      "customSize": true,
      "depth": 1,
      "height": 92,
      "layer": "yes_no",
      "name": "YesNoTitle",
      "persistentUuid": "2dac99b0-92da-4360-b276-48261a22d74b",
      "width": 1280,
      "x": 0,
      "y": 314,
      "zOrder": 3,
      "numberProperties": [],
      "stringProperties": [],
      "initialVariables": []
    }
  ],
  "editionSettings": {
    "grid": false,
    "gridType": "rectangular",
    "gridWidth": 32,
    "gridHeight": 32,
    "gridOffsetX": 0,
    "gridOffsetY": 0,
    "gridColor": 10401023,
    "gridAlpha": 0.8,
    "snap": false,
    "zoomFactor": 0.3300560049165924,
    "windowMask": false
  }
}